secop_ophyd/AsyncFrappyClient.py
secop_ophyd/GenNodeCode.py
secop_ophyd/SECoPDevices.py
secop_ophyd/SECoPSignal.py
secop_ophyd/__init__.py
secop_ophyd/_version.py
secop_ophyd/logs.py
secop_ophyd/propertykeys.py
secop_ophyd/util.py
secop_ophyd-0.13.7.dist-info/licenses/LICENSE
secop_ophyd-0.13.7.dist-info/METADATA
secop_ophyd-0.13.7.dist-info/WHEEL
secop_ophyd-0.13.7.dist-info/top_level.txt
secop_ophyd-0.13.7.dist-info/RECORD
