Metadata-Version: 2.4
Name: secop-ophyd
Version: 0.13.7
Summary: An Interface between bluesky and SECoP, using ophyd and frappy-client
Author-email: Peter Braun <peter.braun@helmholtz-berlin.de>
License:                     GNU GENERAL PUBLIC LICENSE
Requires-Python: >=3.10
License-File: LICENSE
Requires-Dist: ophyd-async>=0.10.0
Requires-Dist: frappy-core==0.20.4
Provides-Extra: dev
Requires-Dist: isort; extra == "dev"
Requires-Dist: pytest==7.4.2; extra == "dev"
Requires-Dist: black; extra == "dev"
Requires-Dist: flake8; extra == "dev"
Requires-Dist: flake8-isort==6.1.1; extra == "dev"
Requires-Dist: pep8-naming; extra == "dev"
Requires-Dist: Flake8-pyproject; extra == "dev"
Requires-Dist: mypy; extra == "dev"
Requires-Dist: wheel; extra == "dev"
Requires-Dist: cycler; extra == "dev"
Requires-Dist: mlzlog; extra == "dev"
Requires-Dist: matplotlib; extra == "dev"
Requires-Dist: pytest-asyncio; extra == "dev"
Requires-Dist: pytest-xprocess; extra == "dev"
Requires-Dist: pytest-cov; extra == "dev"
Requires-Dist: pre-commit; extra == "dev"
Requires-Dist: ipykernel; extra == "dev"
Requires-Dist: databroker[all]==2.0.0b64; extra == "dev"
Requires-Dist: ophyd; extra == "dev"
Requires-Dist: tox; extra == "dev"
Requires-Dist: mlzlog; extra == "dev"
Requires-Dist: python-dotenv; extra == "dev"
Requires-Dist: bluesky; extra == "dev"
Requires-Dist: sphinx; extra == "dev"
Requires-Dist: snakefmt; extra == "dev"
Dynamic: license-file
